easy_upload-0.1.2.dist-info/METADATA
easy_upload-0.1.2.dist-info/WHEEL
easy_upload-0.1.2.dist-info/entry_points.txt
easy_upload-0.1.2.dist-info/licenses/LICENSE
easy_upload/__init__.py
easy_upload/cli.py
easy_upload/commands/repo.py
easy_upload/commands/upload.py
easy_upload/lib/credentials.py
easy_upload/lib/repo.py
easy_upload/lib/upload.py
easy_upload/lib/users.py
easy_upload-0.1.2.dist-info/RECORD
