Metadata-Version: 2.1
Name: easy_upload
Version: 0.1.2
Summary: User-friendly Twine alternative for PyPI.
Author-Email: AmaseCocoa <cocoa@amase.cc>
License: MIT
Requires-Python: >=3.9
Requires-Dist: typer>=0.15.1
Requires-Dist: twine>=6.1.0
Requires-Dist: keyring>=25.6.0
Requires-Dist: beaupy>=3.10.1
Requires-Dist: tomlkit>=0.13.2
Requires-Dist: pyfiglet>=1.0.2
